plurally/__init__.py
plurally/auth/__init__.py
plurally/auth/abstract_oauth.py
plurally/auth/abstract_token.py
plurally/auth/oauth.py
plurally/auth/token.py
plurally/crypto.py
plurally/datetime_utils.py
plurally/demo/__init__.py
plurally/demo/batch.py
plurally/demo/ceva1.json
plurally/demo/clear_salesforce.py
plurally/demo/enky.json
plurally/demo/flows/cr_commercial.yaml
plurally/demo/flows/expo_corsight.yaml
plurally/demo/flows/expo_enky.yaml
plurally/demo/flows/expo_notes.yaml
plurally/demo/flows/expo_onfire.yaml
plurally/demo/flows/hyline_farm_visit.yaml
plurally/demo/flows/hyline_general_visit.yaml
plurally/demo/flows/latitude_sheet.yaml
plurally/demo/flows/meeting.yaml
plurally/demo/flows/meeting_corsight.yaml
plurally/demo/flows/meeting_enky.yaml
plurally/demo/flows/sncf.yaml
plurally/demo/flows/sos_medecins1.yaml
plurally/demo/flows/sos_medecins2.yaml
plurally/demo/flows/v2tu_list.yaml
plurally/demo/flows/vet_urgentys.yaml
plurally/demo/flows/vet_urgentys_list.yaml
plurally/demo/sales.py
plurally/demo/salesforce.json
plurally/demo/salestest.py
plurally/demo/toyaml.py
plurally/demo/vet.html
plurally/demo/vet_urgentys_compare.py
plurally/json_utils.py
plurally/llm/llm_utils.py
plurally/llm/templates/examples.jinja2
plurally/llm/templates/general_info.jinja2
plurally/localization/template.py
plurally/localization/translations/auto_tl.py
plurally/localization/translations/en/LC_MESSAGES/merged.mo
plurally/localization/translations/en/LC_MESSAGES/messages.po
plurally/localization/translations/en/LC_MESSAGES/salesforce.po
plurally/localization/translations/fr/LC_MESSAGES/merged.mo
plurally/localization/translations/fr/LC_MESSAGES/messages.po
plurally/localization/translations/fr/LC_MESSAGES/salesforce.po
plurally/localization/translations/tl.py
plurally/main.py
plurally/models/__init__.py
plurally/models/action/__init__.py
plurally/models/action/ai.py
plurally/models/action/arithmetic.py
plurally/models/action/complete.py
plurally/models/action/email_smtp.py
plurally-0.3.76.dist-info/METADATA
plurally-0.3.76.dist-info/WHEEL
plurally-0.3.76.dist-info/RECORD
