Metadata-Version: 2.1
Name: plurally
Version: 0.3.76
Summary: 
Author: Alexandre Villard
Author-email: alexvillard67@gmail.com
Requires-Python: >=3.10,<4.0
Classifier: Programming Language :: Python :: 3
Classifier: Programming Language :: Python :: 3.10
Classifier: Programming Language :: Python :: 3.11
Classifier: Programming Language :: Python :: 3.12
Classifier: Programming Language :: Python :: 3.13
Requires-Dist: babel (>=2.16.0,<3.0.0)
Requires-Dist: beautifulsoup4 (>=4.12.3,<5.0.0)
Requires-Dist: croniter (>=3.0.3,<4.0.0)
Requires-Dist: cryptography (>=43.0.0,<44.0.0)
Requires-Dist: datamodel-code-generator (>=0.28.1,<0.29.0)
Requires-Dist: dateparser (>=1.2.0,<2.0.0)
Requires-Dist: dpath (>=2.2.0,<3.0.0)
Requires-Dist: email-validator (>=2.2.0,<3.0.0)
Requires-Dist: faiss-cpu (>=1.8.0.post1,<2.0.0)
Requires-Dist: google-api-python-client (>=2.144.0,<3.0.0)
Requires-Dist: google-auth (>=2.34.0,<3.0.0)
Requires-Dist: hubspot-api-client (>=10.0.0,<11.0.0)
Requires-Dist: instructor[mistral] (>=1.7.9,<2.0.0)
Requires-Dist: jinja2schema (>=0.1.4,<0.2.0)
Requires-Dist: jsonref (>=1.1.0,<2.0.0)
Requires-Dist: litellm (>=1.44.22,<2.0.0)
Requires-Dist: loguru (>=0.7.2,<0.8.0)
Requires-Dist: networkx[default] (>=3.3,<4.0)
Requires-Dist: pydantic (==2.9.2)
Requires-Dist: pydantic-extra-types (>=2.9.0,<3.0.0)
Requires-Dist: pytz (>=2024.2,<2025.0)
Requires-Dist: rq (>=2.0.0,<3.0.0)
Requires-Dist: ruamel-yaml (<0.18.0)
Requires-Dist: sentry-sdk[rq] (>=2.17.0,<3.0.0)
Requires-Dist: simple-salesforce (>=1.12.6,<2.0.0)
Requires-Dist: thefuzz (>=0.22.1,<0.23.0)
Requires-Dist: weasyprint (>=63.0,<64.0)
